oef/Interfaces.py
oef/Logging.py
oef/ProtoHelpers.py
oef/QueryBuildingBlocks.py
oef/TypeHelpers.py
oef/Wrappers.py
oef/__init__.py
oef/__version__.py
oef/agent_pb2.py
oef/agents.py
oef/core.py
oef/dap_interface_pb2.py
oef/fipa_pb2.py
oef/helpers.py
oef/messages.py
oef/protostuff.py
oef/proxy.py
oef/query.py
oef/schema.py
oef/setup.py
oef/uri.py
oef-0.8.1.dist-info/METADATA
oef-0.8.1.dist-info/WHEEL
oef-0.8.1.dist-info/top_level.txt
oef-0.8.1.dist-info/RECORD
