Metadata-Version: 2.1
Name: oef
Version: 0.8.1
Summary: SDK for OEF Agent development.
Home-page: https://github.com/fetchai/oef-sdk-python.git
Author: Fetch.AI Limited
Author-email: community@fetch.ai
License: Apache 2.0
Platform: UNKNOWN
Classifier: Development Status :: 3 - Alpha
Classifier: Intended Audience :: Developers
Classifier: Natural Language :: English
Classifier: License :: OSI Approved :: Apache Software License
Classifier: Programming Language :: Python :: 3.6
Classifier: Programming Language :: Python :: 3.7
Requires-Python: >=3.6
Requires-Dist: protobuf
Requires-Dist: graphviz
